{
	"id": "_2w9stzngk",
	"title": "HTML Inputs",
	"difficulty": "easy",
	"steps": [
		{
			"type": "dom",
			"desc": "Forms give you a way to let the user interact with your website. The most common input field is a text field.",
			"render": true,
			"action": [
				"<input type=\"text\" placeholder=\"Favorite Ice Cream\">"
			]
		},
		{
			"type": "dom",
			"desc": "Radio buttons allow the user to select one of many options.",
			"render": true,
			"action": [
				"<label>Vanilla</label>",
				"<input type=\"radio\" name=\"flavor\" value=\"vanilla\">",
				"<label>Chocolate</label>",
				"<input type=\"radio\" name=\"flavor\" value=\"chocolate\">",
				""
			]
		},
		{
			"type": "dom",
			"desc": "Checkboxes allow the user to click more than one option.",
			"render": true,
			"action": [
				"<label>Vanilla</label>",
				"<input type=\"checkbox\" name=\"flavor\" value=\"vanilla\">",
				"<label>Chocolate</label>",
				"<input type=\"checkbox\" name=\"flavor\" value=\"chocolate\">",
				""
			]
		},
		{
			"type": "dom",
			"desc": "Sometimes, the user has a lot to type. Thankfully, HTML has a text area that allows users to type as much as they need.",
			"render": true,
			"action": [
				"<textarea name=\"special-info\" cols=\"20\" rows=\"20\"></textarea>"
			]
		},
		{
			"type": "dom",
			"desc": "The web is full of forms. All form elements should be wrapped inside a form tag to get the full benefit.",
			"render": true,
			"action": [
				"<form>",
				"  <label>Do you like Ice Cream?</label>",
				"  <input type=\"checkbox\" value=\"yes\">",
				"  <label>What flavor?</label>",
				"  <input type=\"text\" placeholder=\"\">",
				"</form>"
			]
		},
		{
			"type": "dom",
			"desc": "All forms need to be \"submitted\", so let's give every form a submit button",
			"render": true,
			"action": [
				"<input type=\"submit\" value=\"Make Ice Cream\">"
			]
		}
	]
}
